pocket_git/__init__.py
pocket_git/__main__.py
pocket_git/commands.py
pocket_git/core.py
pocket_git-0.1.1.dist-info/licenses/LICENSE
pocket_git-0.1.1.dist-info/METADATA
pocket_git-0.1.1.dist-info/WHEEL
pocket_git-0.1.1.dist-info/entry_points.txt
pocket_git-0.1.1.dist-info/top_level.txt
pocket_git-0.1.1.dist-info/RECORD
