Metadata-Version: 2.4
Name: pocket-git
Version: 0.1.1
Summary: A minimal git implementation that fits in your pocket
Home-page: https://github.com/vibey19/pocket-git
Author: Jainil Dadhaniya
Author-email: Jainil Dadhaniya <jdadhaniya6@gmail.com>
License-Expression: MIT
Classifier: Intended Audience :: Education
Classifier: Programming Language :: Python :: 3
Requires-Python: >=3.8
License-File: LICENSE
Dynamic: author
Dynamic: home-page
Dynamic: license-file
Dynamic: requires-python
